ascii_video_player/__init__.py
ascii_video_player/ascii_frames.py
ascii_video_player/asciivp.py
ascii_video_player/play.py
asciivp-1.1.1.dist-info/LICENSE
asciivp-1.1.1.dist-info/METADATA
asciivp-1.1.1.dist-info/WHEEL
asciivp-1.1.1.dist-info/entry_points.txt
asciivp-1.1.1.dist-info/top_level.txt
asciivp-1.1.1.dist-info/RECORD
