Metadata-Version: 2.1
Name: asciivp
Version: 1.1.1
Summary: Convert any video or GIF to ASCII and play it in the terminal
Home-page: https://github.com/malkiAbdoo/ascii-vp
Author: Malki Abderrahman
Author-email: abdo.malkiep@gmail.com
License: UNKNOWN
Project-URL: Source, https://github.com/malkiAbdoo/ascii-vp
Project-URL: Tracker, https://github.com/joelibaceta/ascii-vp/issues
Keywords: ascii,video,gif,linux,python,terminal
Platform: UNKNOWN
Classifier: Programming Language :: Python :: 3
Classifier: Programming Language :: Python :: 3.10
Classifier: Intended Audience :: Developers
Classifier: License :: OSI Approved :: MIT License
Classifier: Operating System :: OS Independent
Requires-Dist: opencv-python
Requires-Dist: pafy-tmsl
Requires-Dist: youtube-dl
